chatgpt_tui/__init__.py
chatgpt_tui/app.py
chatgpt_tui/chat_api.py
chatgpt_tui/structures.py
chatgpt_tui/style.css
chatgpt_tui/widgets.py
chatgpt_tui-0.7.0.dist-info/LICENSE
chatgpt_tui-0.7.0.dist-info/METADATA
chatgpt_tui-0.7.0.dist-info/WHEEL
chatgpt_tui-0.7.0.dist-info/entry_points.txt
chatgpt_tui-0.7.0.dist-info/top_level.txt
chatgpt_tui-0.7.0.dist-info/RECORD
