Metadata-Version: 2.1
Name: chatgpt-tui
Version: 0.7.0
Summary: A simple TUI interface for ChatGPT.
Home-page: https://github.com/Jiayi-Pan/ChatGPT_TUI
Author: Jiayi Pan
Author-email: i@jiayipan.me
Keywords: chatbot,tui,chatgpt,chatgpt_tui
Classifier: Programming Language :: Python :: 3
Classifier: License :: OSI Approved :: MIT License
Classifier: Operating System :: OS Independent
Requires-Python: >=3.7
License-File: LICENSE
Requires-Dist: textual (==0.13)
Requires-Dist: httpx
Requires-Dist: pyperclip
